[{"page":1,"y":1168,"text":"ENDEREÇO DE ENTREGA:"},{"page":1,"y":1155,"text":"RUA CAETES, Q. 9, L. 1/7, S/N, | - C/ AV TAMOIOS"},{"page":1,"y":1148,"text":"JARDIM ELDORADO"},{"page":1,"y":1140,"text":"Segunda via | CEP: 74993040 APARECIDA DE GOIANIA GO BRASIL"},{"page":1,"y":1108,"text":"Classificação: A OPT B3 COMERCIAL OU SERVIÇOS E OUTRAS ATIVIDADES -"},{"page":1,"y":1098,"text":"SERVIÇOS E OUTRAS ATIVIDADES OPTANTE_B | Tipo de Fornecimento: TRIFÁSICO"},{"page":1,"y":1088,"text":"Tensão Nominal Disp: 13800 V | Lim Min: 12.834 V | Lim Max: 14.490 V"},{"page":1,"y":1073,"text":"31/03/2026 | 30/04/2026 | 30 | 31/05/2026"},{"page":1,"y":1065,"text":"TAC LOGISTICA LTDA"},{"page":1,"y":1056,"text":"CNPJ/CPF: 01.456.021/0001-89 | INSC. ESTADUAL:"},{"page":1,"y":1047,"text":"RUA CAETES, Q. 9, L. 1/7, S/N, | - C/ AV TAMOIOS"},{"page":1,"y":1036,"text":"JARDIM ELDORADO | NOTA FISCAL Nº 192548872 - SÉRIE 0 / DATA DE EMISSÃO: 21/05/2026 13:34:20"},{"page":1,"y":1028,"text":"CEP: 74993040 APARECIDA DE GOIANIA GO BRASIL"},{"page":1,"y":1019,"text":"PERDAS DE TRANSFORMAÇÃO / RAMAL: 0 %"},{"page":1,"y":1014,"text":"1.086.729.012-25 | Consulte pela Chave de Acesso em:"},{"page":1,"y":1003,"text":"https://dfe-portal.svrs.rs.gov.br/NF3e/consulta"},{"page":1,"y":993,"text":"chave de acesso:"},{"page":1,"y":983,"text":"52260501543032000104660001925488721090171870"},{"page":1,"y":973,"text":"Protocolo de autorização: 3522600016616538 - 21/05/2026 às 13:34:34"},{"page":1,"y":963,"text":"CFOP 5253: Venda de energia elétrica para estabelecimento comercial"},{"page":1,"y":928,"text":"MAI/2026 | R$*******1.481,14 | 03/06/2026"},{"page":1,"y":881,"text":"ESTA UC NÃO POSSUI DÉBITOS RELATIVOS AOS ANOS DE 2025 E ANTERIORES. ESTA DECLARAÇÃO É COMPROVANTE DE PAGAMENTO, EXCETO QUANTO À DÍVIDA AINDA NÃO APURADA ATÉ ESTA DATA OU SUB JUDICE. LEI 12.007/2009."},{"page":1,"y":872,"text":"PERÍODO DE REFERÊNCIA DA APURAÇÃO DOS INDICADORES DE CONTINUIDADE = 3/2026. VRC = R$ 283,95643"},{"page":1,"y":772,"text":"PIS/PASEP | 1119,07 | 0,3931% | 4,4"},{"page":1,"y":761,"text":"FORNECIMENTO | ICMS | 1381,58 | 19% | 262,5"},{"page":1,"y":749,"text":"CONSUMO FP | kWh | 672 | 1,126017 | 756,68 | 13,62 | 756,68 | 19% | 143,77 | 0,891810 | COFINS | 1119,07 | 1,8287% | 20,46"},{"page":1,"y":739,"text":"CONSUMO HR | kWh | 315 | 1,126017 | 354,70 | 6,38 | 354,7 | 19% | 67,39 | 0,891810"},{"page":1,"y":729,"text":"CONSUMO P | kWh | 129,36 | 1,126017 | 145,66 | 2,62 | 145,66 | 19% | 27,68 | 0,891810"},{"page":1,"y":719,"text":"UFER FP | kVArh | 273 | 0,409265 | 111,73 | 2,01 | 111,73 | 19% | 21,23 | 0,324140"},{"page":1,"y":709,"text":"UFER P | kVArh | 31,29 | 0,409265 | 12,81 | 0,23 | 12,81 | 19% | 2,43 | 0,324140"},{"page":1,"y":700,"text":"ITENS FINANCEIROS"},{"page":1,"y":688,"text":"CONTRIB. ILUM. PÚBLICA - MUNICIPAL | 99,56 | DEMANDA - kW | 0"},{"page":1,"y":518,"text":"TOTAL | 1.481,14 | 24,86 | 1.381,58 | 262,50"},{"page":1,"y":470,"text":"12107955-4 | ENERGIA ATIVA - KWH | PONTA | 063973 | 064589 | 0,210000 | 129,36"},{"page":1,"y":461,"text":"12107955-4 | ENERGIA ATIVA - KWH | FORA PONTA | 004426 | 004458 | 21,000000 | 672"},{"page":1,"y":452,"text":"12107955-4 | ENERGIA ATIVA - KWH | RESERVADO | 001657 | 001672 | 21,000000 | 315"},{"page":1,"y":442,"text":"12107955-4 | DEMANDA - KW | PONTA | 000701 | 000706 | 0,840000 | 4,2 | 37,21 | 25/05/2026"},{"page":1,"y":434,"text":"12107955-4 | DEMANDA - KW | FORA PONTA | 000902 | 000909 | 0,840000 | 5,88"},{"page":1,"y":429,"text":"1132,43"},{"page":1,"y":425,"text":"12107955-4 | DEMANDA - KW | RESERVADO | 000650 | 000654 | 0,840000 | 3,36"},{"page":1,"y":416,"text":"12107955-4 | UFER | PONTA | 009680 | 009829 | 0,210000 | 31,29"},{"page":1,"y":407,"text":"12107955-4 | UFER | FORA PONTA | 001033 | 001046 | 21,000000 | 273"},{"page":1,"y":398,"text":"12107955-4 | UFER | RESERVADO | 000000 | 000000 | 21,000000 | 0 | 3544/25"},{"page":1,"y":389,"text":"12107955-4 | DMCR | PONTA | 002552 | 002572 | 0,210000 | 4,2"},{"page":1,"y":380,"text":"12107955-4 | DMCR | FORA PONTA | 003496 | 003520 | 0,210000 | 5,04"},{"page":1,"y":304,"text":"NOTIFICAÇÃO: 1 FATURA VENCIDA: MÊS 4/2026 VALOR TOTAL: R$ 1.532,37 (DESCONSIDERE SE FOI PAGO)."},{"page":1,"y":294,"text":"A SUSPENSÃO DO FORNECIMENTO OCORRERÁ APÓS O DIA 09/06/2026 OU A QUALQUER MOMENTO POR DÉBITOS JÁ REAVISADOS ANTERIORMENTE."},{"page":1,"y":202,"text":"BANCO DO BRASIL | 001-9 | 00190.00009 03810.643043 12248.326170 7 14660000148114"},{"page":1,"y":184,"text":"PAGÁVEL EM QUALQUER BANCO | 03/06/2026"},{"page":1,"y":167,"text":"EQUATORIAL GOIAS DISTRIBUIDORA DE ENERGIA S/A | 1.086.729.012-25 | MAI/2026"},{"page":1,"y":148,"text":"22/05/2026 | 2026049703187 | MN | 22/05/2026 | 38106430412248326"},{"page":1,"y":131,"text":"17 | R$ | 1.481,14"},{"page":1,"y":109,"text":"O Pagamento poderá ser realizado 1 dia útil após a emissão. Para cadastrar sua fatura em débito automático utilize o código 0200546624"},{"page":1,"y":85,"text":"TAC LOGISTICA LTDA | CNPJ/CPF: 01.456.021/0001-89"},{"page":1,"y":78,"text":"RUA CAETES, Q. 9, L. 1/7, S/N, | - C/ AV TAMOIOS JARDIM ELDORADO CEP: 74993040 APARECIDA DE GOIANIA GO BRASIL"},{"page":1,"y":23,"text":"SE PREFERIR, COPIE E COLE O CÓDIGO"},{"page":1,"y":13,"text":"CÓDIGO DO PIX: | PIX ABAIXO PARA FAZER O PAGAMENTO"},{"page":1,"y":6,"text":"00020101021226900014br.gov.bcb.pix2568qrcodepix.bb.com.br/pix/v2/cobv/36b4c7c8-459e-486d-aca8-7ef0316d49475204000053039865802BR5916EQUATORIAL GOIAS6007GOIANIA6217051320260497031876304D75F"},{"page":2,"y":915,"text":"MAI / 26 | 4,2000 | 5,8800 | 0,0000 | 129,36 | 672,00 | 304,29 | 315,00 | 0,00 | 0,00 | 0.00"},{"page":2,"y":900,"text":"ABR / 26 | 5,0400 | 6,7200 | 0,0000 | 98,07 | 756,00 | 397,95 | 273,00 | 0,00 | 0,00 | 0.00"},{"page":2,"y":885,"text":"MAR / 26 | 4,2000 | 7,5600 | 0,0000 | 90,93 | 630,00 | 400,68 | 252,00 | 0,00 | 0,00 | 0.00"},{"page":2,"y":870,"text":"FEV / 26 | 3,3600 | 5,8800 | 0,0000 | 105,00 | 714,00 | 303,66 | 294,00 | 0,00 | 0,00 | 0.00"},{"page":2,"y":855,"text":"JAN / 26 | 4,2000 | 7,5600 | 0,0000 | 114,03 | 714,00 | 303,45 | 294,00 | 0,00 | 0,00 | 0.00"},{"page":2,"y":840,"text":"DEZ / 25 | 3,3600 | 6,7200 | 0,0000 | 99,12 | 714,00 | 390,18 | 315,00 | 0,00 | 0,00 | 0.00"},{"page":2,"y":825,"text":"NOV / 25 | 5,0400 | 5,8800 | 0,0000 | 128,73 | 693,00 | 347,97 | 315,00 | 0,00 | 0,00 | 0.00"},{"page":2,"y":810,"text":"OUT / 25 | 5,0400 | 6,7200 | 0,0000 | 136,29 | 798,00 | 296,52 | 357,00 | 0,00 | 0,00 | 0.00"},{"page":2,"y":795,"text":"SET / 25 | 6,7200 | 6,7200 | 0,0000 | 145,53 | 819,00 | 274,05 | 378,00 | 0,00 | 0,00 | 0.00"},{"page":2,"y":780,"text":"AGO / 25 | 7,5600 | 7,5600 | 0,0000 | 143,85 | 777,00 | 412,44 | 315,00 | 0,00 | 0,00 | 0.00"},{"page":2,"y":765,"text":"JUL / 25 | 6,7200 | 6,7200 | 0,0000 | 115,92 | 672,00 | 365,61 | 273,00 | 0,00 | 0,00 | 0.00"},{"page":2,"y":750,"text":"JUN / 25 | 5,8800 | 7,5600 | 0,0000 | 102,27 | 651,00 | 205,59 | 189,00 | 0,00 | 0,00 | 0.00"},{"page":2,"y":735,"text":"MAI / 25 | 0,0000 | 0,0000 | 0,0000 | 0,00 | 0,00 | 157,92 | 0,00 | 0,00 | 0,00 | 0.00"},{"page":2,"y":702,"text":"3544/25"},{"page":2,"y":669,"text":"672,00"},{"page":2,"y":646,"text":"129,36"},{"page":2,"y":624,"text":"0,0000"}]